sileopy/__init__.py
sileopy/api_functions.py
sileopy/common_functions.py
sileopy/data_validation.py
sileopy/file_objects.py
sileopy/ftp_functions.py
sileopy/opsgenie_objects.py
sileopy-0.1.1.dist-info/WHEEL
sileopy-0.1.1.dist-info/METADATA
sileopy-0.1.1.dist-info/RECORD
