Metadata-Version: 2.1
Name: sileopy
Version: 0.1.1
Summary: Ett bibliotek för python-moduler med allmän funktionalitet som kan vara användbar i flera projekt.
Author: Johan Magnusson
Author-email: johan.magnusson@sileokapital.com
Requires-Python: >=3.7,<4.0
Classifier: Programming Language :: Python :: 3
Classifier: Programming Language :: Python :: 3.10
Classifier: Programming Language :: Python :: 3.7
Classifier: Programming Language :: Python :: 3.8
Classifier: Programming Language :: Python :: 3.9
Requires-Dist: opsgenie-sdk (>=2.1.5,<3.0.0)
Requires-Dist: paramiko (>=2.11.0,<3.0.0)
Requires-Dist: requests (>=2.28.1,<3.0.0)
